odoo8_addon_logistic_requisition-8.0.1.4.1-py2.7-nspkg.pth
odoo_addons/logistic_requisition/__openerp__.py
odoo_addons/logistic_requisition/__init__.py
odoo_addons/logistic_requisition/logistic_requisition_report.xml
odoo_addons/logistic_requisition/README.rst
odoo_addons/logistic_requisition/security/logistic_requisition.xml
odoo_addons/logistic_requisition/security/ir.model.access.csv
odoo_addons/logistic_requisition/view/sale_order.xml
odoo_addons/logistic_requisition/view/purchase_order.xml
odoo_addons/logistic_requisition/view/report_logistic_requisition.xml
odoo_addons/logistic_requisition/view/stock.xml
odoo_addons/logistic_requisition/view/cancel_reason.xml
odoo_addons/logistic_requisition/view/logistic_requisition.xml
odoo_addons/logistic_requisition/i18n/logistic_requisition.pot
odoo_addons/logistic_requisition/i18n/en_US.po
odoo_addons/logistic_requisition/model/stock.py
odoo_addons/logistic_requisition/model/purchase.py
odoo_addons/logistic_requisition/model/purchase_requisition.py
odoo_addons/logistic_requisition/model/logistic_requisition.py
odoo_addons/logistic_requisition/model/sale_order.py
odoo_addons/logistic_requisition/model/__init__.py
odoo_addons/logistic_requisition/model/procurement.py
odoo_addons/logistic_requisition/model/requisition_cancel.py
odoo_addons/logistic_requisition/wizard/assign_line_view.xml
odoo_addons/logistic_requisition/wizard/cost_estimate.py
odoo_addons/logistic_requisition/wizard/logistic_requisition_cancel_view.xml
odoo_addons/logistic_requisition/wizard/logistic_requisition_cancel.py
odoo_addons/logistic_requisition/wizard/assign_line.py
odoo_addons/logistic_requisition/wizard/__init__.py
odoo_addons/logistic_requisition/wizard/quotation_sourcing.py
odoo_addons/logistic_requisition/wizard/cost_estimate_view.xml
odoo_addons/logistic_requisition/test/requisition_create_cost_estimate.yml
odoo_addons/logistic_requisition/test/logistic_requisition_report_test.yml
odoo8_addon_logistic_requisition-8.0.1.4.1.dist-info/top_level.txt
odoo8_addon_logistic_requisition-8.0.1.4.1.dist-info/WHEEL
odoo8_addon_logistic_requisition-8.0.1.4.1.dist-info/RECORD
odoo8_addon_logistic_requisition-8.0.1.4.1.dist-info/metadata.json
odoo8_addon_logistic_requisition-8.0.1.4.1.dist-info/DESCRIPTION.rst
odoo8_addon_logistic_requisition-8.0.1.4.1.dist-info/METADATA
odoo8_addon_logistic_requisition-8.0.1.4.1.dist-info/namespace_packages.txt
