Metadata-Version: 2.0
Name: odoo8-addon-logistic-requisition
Version: 8.0.1.4.1
Summary: Logistics Requisition
Home-page: http://www.camptocamp.com
Author: UNKNOWN
Author-email: UNKNOWN
License: AGPL-3
Platform: UNKNOWN
Requires-Dist: odoo (<9.0a,>=8.0a)
Requires-Dist: odoo8-addon-logistic-consignee
Requires-Dist: odoo8-addon-logistic-order
Requires-Dist: odoo8-addon-ngo-purchase
Requires-Dist: odoo8-addon-purchase-requisition-bid-selection
Requires-Dist: odoo8-addon-purchase-requisition-transport-document
Requires-Dist: odoo8-addon-purchase-requisition-transport-multi-address
Requires-Dist: odoo8-addon-sale-owner-stock-sourcing
Requires-Dist: odoo8-addon-sale-sourced-by-line
Requires-Dist: odoo8-addon-sale-transport-multi-address
Requires-Dist: odoo8-addon-transport-information
Requires-Dist: odoo8-addon-web-context-tunnel
Classifier: Programming Language :: Python :: 2.7
Classifier: Framework :: Odoo
Classifier: License :: OSI Approved :: GNU Affero General Public License v3
